reqflow/__init__.py
reqflow/assertions.py
reqflow/client.py
reqflow/exceptions.py
reqflow/fluent_api.py
reqflow/response/__init__.py
reqflow/response/response.py
reqflow/utils/__init__.py
reqflow/utils/constants.py
reqflow/utils/logger.py
reqflow/validator/__init__.py
reqflow/validator/validator.py
tests/__init__.py
tests/conftest.py
tests/test_assertions.py
tests/test_async.py
tests/test_basic_auth.py
tests/test_client.py
tests/test_cookies.py
tests/test_embedded_client.py
tests/test_file_io.py
tests/test_fluent_api.py
tests/test_headers.py
tests/test_logger.py
tests/test_oauth2_auth.py
tests/test_response.py
tests/test_validator.py
tests/test_validator_pydantic_constraints.py
ReqFlow-1.1.0a0.dist-info/LICENSE
ReqFlow-1.1.0a0.dist-info/METADATA
ReqFlow-1.1.0a0.dist-info/WHEEL
ReqFlow-1.1.0a0.dist-info/top_level.txt
ReqFlow-1.1.0a0.dist-info/RECORD
