Metadata-Version: 2.1
Name: ReqFlow
Version: 1.1.0a0
Summary: A streamlined Python library for crafting HTTP requests and testing API
Home-page: https://github.com/olxxi/ReqFlow
Author: Oleksii P.
License: UNKNOWN
Platform: UNKNOWN
Requires-Python: >=3.8
License-File: LICENSE
Requires-Dist: httpx >=0.26.0
Requires-Dist: jsonpath-ng >=1.6.1
Requires-Dist: pydantic >=2.5.3
